{"Sport": {"Barueri": {"Win": 0, "Loss": 0, "Draw": 1}, "Atletico-MG": {"Win": 0, "Loss": 1, "Draw": 0}, "Flamengo": {"Win": 1, "Loss": 0, "Draw": 0}, "Athletico-PR": {"Win": 0, "Loss": 1, "Draw": 0}, "Gremio": {"Win": 1, "Loss": 0, "Draw": 0}, "Goias": {"Win": 1, "Loss": 0, "Draw": 0}, "Avai": {"Win": 0, "Loss": 1, "Draw": 0}, "Nautico": {"Win": 0, "Loss": 0, "Draw": 1}, "Palmeiras": {"Win": 0, "Loss": 1, "Draw": 0}, "Sao Paulo": {"Win": 0, "Loss": 1, "Draw": 0}, "Vitoria": {"Win": 1, "Loss": 0, "Draw": 0}, "Botafogo-RJ": {"Win": 1, "Loss": 0, "Draw": 0}, "Santo Andre": {"Win": 1, "Loss": 0, "Draw": 0}, "Santos": {"Win": 0, "Loss": 1, "Draw": 0}, "Corinthians": {"Win": 1, "Loss": 0, "Draw": 0}, "Coritiba": {"Win": 0, "Loss": 0, "Draw": 1}, "Cruzeiro": {"Win": 0, "Loss": 1, "Draw": 0}, "Fluminense": {"Win": 0, "Loss": 1, "Draw": 0}, "Internacional": {"Win": 0, "Loss": 1, "Draw": 0}}, "Palmeiras": {"Coritiba": {"Win": 1, "Loss": 0, "Draw": 0}, "Sao Paulo": {"Win": 0, "Loss": 0, "Draw": 1}, "Cruzeiro": {"Win": 1, "Loss": 0, "Draw": 0}, "Vitoria": {"Win": 1, "Loss": 0, "Draw": 0}, "Santos": {"Win": 0, "Loss": 0, "Draw": 1}, "Nautico": {"Win": 1, "Loss": 0, "Draw": 0}, "Santo Andre": {"Win": 1, "Loss": 0, "Draw": 0}, "Fluminense": {"Win": 1, "Loss": 0, "Draw": 0}, "Gremio": {"Win": 0, "Loss": 0, "Draw": 1}, "Botafogo-RJ": {"Win": 0, "Loss": 0, "Draw": 1}, "Internacional": {"Win": 1, "Loss": 0, "Draw": 0}, "Barueri": {"Win": 1, "Loss": 0, "Draw": 0}, "Athletico-PR": {"Win": 1, "Loss": 0, "Draw": 0}, "Avai": {"Win": 0, "Loss": 0, "Draw": 1}, "Flamengo": {"Win": 0, "Loss": 1, "Draw": 0}, "Goias": {"Win": 1, "Loss": 0, "Draw": 0}, "Corinthians": {"Win": 0, "Loss": 0, "Draw": 1}, "Sport": {"Win": 0, "Loss": 0, "Draw": 1}, "Atletico-MG": {"Win": 1, "Loss": 0, "Draw": 0}}, "Avai": {"Atletico-MG": {"Win": 0, "Loss": 0, "Draw": 1}, "Coritiba": {"Win": 0, "Loss": 0, "Draw": 1}, "Sao Paulo": {"Win": 0, "Loss": 0, "Draw": 1}, "Fluminense": {"Win": 1, "Loss": 0, "Draw": 0}, "Palmeiras": {"Win": 0, "Loss": 1, "Draw": 0}, "Botafogo-RJ": {"Win": 0, "Loss": 1, "Draw": 0}, "Gremio": {"Win": 1, "Loss": 0, "Draw": 0}, "Vitoria": {"Win": 1, "Loss": 0, "Draw": 0}, "Santo Andre": {"Win": 1, "Loss": 0, "Draw": 0}, "Nautico": {"Win": 1, "Loss": 0, "Draw": 0}, "Flamengo": {"Win": 1, "Loss": 0, "Draw": 0}, "Internacional": {"Win": 0, "Loss": 1, "Draw": 0}, "Barueri": {"Win": 1, "Loss": 0, "Draw": 0}, "Cruzeiro": {"Win": 0, "Loss": 0, "Draw": 1}, "Goias": {"Win": 1, "Loss": 0, "Draw": 0}, "Sport": {"Win": 0, "Loss": 0, "Draw": 1}, "Athletico-PR": {"Win": 1, "Loss": 0, "Draw": 0}, "Corinthians": {"Win": 1, "Loss": 0, "Draw": 0}, "Santos": {"Win": 0, "Loss": 0, "Draw": 1}}, "Corinthians": {"Internacional": {"Win": 0, "Loss": 1, "Draw": 0}, "Barueri": {"Win": 1, "Loss": 0, "Draw": 0}, "Coritiba": {"Win": 1, "Loss": 0, "Draw": 0}, "Sao Paulo": {"Win": 1, "Loss": 0, "Draw": 0}, "Fluminense": {"Win": 1, "Loss": 0, "Draw": 0}, "Sport": {"Win": 1, "Loss": 0, "Draw": 0}, "Vitoria": {"Win": 1, "Loss": 0, "Draw": 0}, "Palmeiras": {"Win": 0, "Loss": 1, "Draw": 0}, "Avai": {"Win": 0, "Loss": 0, "Draw": 1}, "Atletico-MG": {"Win": 1, "Loss": 0, "Draw": 0}, "Botafogo-RJ": {"Win": 0, "Loss": 0, "Draw": 1}, "Santos": {"Win": 1, "Loss": 0, "Draw": 0}, "Goias": {"Win": 0, "Loss": 1, "Draw": 0}, "Athletico-PR": {"Win": 0, "Loss": 1, "Draw": 0}, "Gremio": {"Win": 1, "Loss": 0, "Draw": 0}, "Cruzeiro": {"Win": 0, "Loss": 1, "Draw": 0}, "Santo Andre": {"Win": 1, "Loss": 0, "Draw": 0}, "Nautico": {"Win": 0, "Loss": 1, "Draw": 0}, "Flamengo": {"Win": 0, "Loss": 1, "Draw": 0}}, "Fluminense": {"Sao Paulo": {"Win": 1, "Loss": 0, "Draw": 0}, "Santos": {"Win": 0, "Loss": 1, "Draw": 0}, "Gremio": {"Win": 0, "Loss": 0, "Draw": 1}, "Botafogo-RJ": {"Win": 1, "Loss": 0, "Draw": 0}, "Flamengo": {"Win": 0, "Loss": 0, "Draw": 1}, "Santo Andre": {"Win": 0, "Loss": 1, "Draw": 0}, "Goias": {"Win": 0, "Loss": 1, "Draw": 0}, "Cruzeiro": {"Win": 0, "Loss": 0, "Draw": 1}, "Sport": {"Win": 1, "Loss": 0, "Draw": 0}, "Coritiba": {"Win": 0, "Loss": 1, "Draw": 0}, "Barueri": {"Win": 0, "Loss": 0, "Draw": 1}, "Nautico": {"Win": 0, "Loss": 0, "Draw": 1}, "Avai": {"Win": 1, "Loss": 0, "Draw": 0}, "Corinthians": {"Win": 0, "Loss": 0, "Draw": 1}, "Internacional": {"Win": 0, "Loss": 0, "Draw": 1}, "Atletico-MG": {"Win": 1, "Loss": 0, "Draw": 0}, "Palmeiras": {"Win": 1, "Loss": 0, "Draw": 0}, "Athletico-PR": {"Win": 1, "Loss": 0, "Draw": 0}, "Vitoria": {"Win": 1, "Loss": 0, "Draw": 0}}, "Athletico-PR": {"Vitoria": {"Win": 0, "Loss": 1, "Draw": 0}, "Nautico": {"Win": 0, "Loss": 1, "Draw": 0}, "Atletico-MG": {"Win": 0, "Loss": 1, "Draw": 0}, "Palmeiras": {"Win": 0, "Loss": 0, "Draw": 1}, "Corinthians": {"Win": 1, "Loss": 0, "Draw": 0}, "Internacional": {"Win": 1, "Loss": 0, "Draw": 0}, "Coritiba": {"Win": 0, "Loss": 0, "Draw": 1}, "Avai": {"Win": 0, "Loss": 1, "Draw": 0}, "Fluminense": {"Win": 1, "Loss": 0, "Draw": 0}, "Barueri": {"Win": 1, "Loss": 0, "Draw": 0}, "Sao Paulo": {"Win": 1, "Loss": 0, "Draw": 0}, "Flamengo": {"Win": 0, "Loss": 0, "Draw": 1}, "Sport": {"Win": 1, "Loss": 0, "Draw": 0}, "Gremio": {"Win": 0, "Loss": 0, "Draw": 1}, "Santo Andre": {"Win": 1, "Loss": 0, "Draw": 0}, "Santos": {"Win": 0, "Loss": 0, "Draw": 1}, "Goias": {"Win": 1, "Loss": 0, "Draw": 0}, "Cruzeiro": {"Win": 0, "Loss": 0, "Draw": 1}, "Botafogo-RJ": {"Win": 1, "Loss": 0, "Draw": 0}}, "Cruzeiro": {"Flamengo": {"Win": 1, "Loss": 0, "Draw": 0}, "Vitoria": {"Win": 1, "Loss": 0, "Draw": 0}, "Internacional": {"Win": 0, "Loss": 0, "Draw": 1}, "Barueri": {"Win": 0, "Loss": 1, "Draw": 0}, "Avai": {"Win": 1, "Loss": 0, "Draw": 0}, "Atletico-MG": {"Win": 0, "Loss": 1, "Draw": 0}, "Corinthians": {"Win": 0, "Loss": 1, "Draw": 0}, "Sport": {"Win": 1, "Loss": 0, "Draw": 0}, "Athletico-PR": {"Win": 0, "Loss": 1, "Draw": 0}, "Santos": {"Win": 0, "Loss": 0, "Draw": 1}, "Nautico": {"Win": 1, "Loss": 0, "Draw": 0}, "Sao Paulo": {"Win": 0, "Loss": 1, "Draw": 0}, "Palmeiras": {"Win": 0, "Loss": 1, "Draw": 0}, "Goias": {"Win": 1, "Loss": 0, "Draw": 0}, "Botafogo-RJ": {"Win": 1, "Loss": 0, "Draw": 0}, "Santo Andre": {"Win": 1, "Loss": 0, "Draw": 0}, "Fluminense": {"Win": 0, "Loss": 1, "Draw": 0}, "Gremio": {"Win": 0, "Loss": 0, "Draw": 1}, "Coritiba": {"Win": 1, "Loss": 0, "Draw": 0}}, "Gremio": {"Santos": {"Win": 0, "Loss": 0, "Draw": 1}, "Botafogo-RJ": {"Win": 1, "Loss": 0, "Draw": 0}, "Nautico": {"Win": 1, "Loss": 0, "Draw": 0}, "Goias": {"Win": 0, "Loss": 0, "Draw": 1}, "Athletico-PR": {"Win": 1, "Loss": 0, "Draw": 0}, "Corinthians": {"Win": 1, "Loss": 0, "Draw": 0}, "Internacional": {"Win": 1, "Loss": 0, "Draw": 0}, "Santo Andre": {"Win": 1, "Loss": 0, "Draw": 0}, "Cruzeiro": {"Win": 1, "Loss": 0, "Draw": 0}, "Flamengo": {"Win": 1, "Loss": 0, "Draw": 0}, "Atletico-MG": {"Win": 1, "Loss": 0, "Draw": 0}, "Vitoria": {"Win": 0, "Loss": 0, "Draw": 1}, "Fluminense": {"Win": 1, "Loss": 0, "Draw": 0}, "Sport": {"Win": 0, "Loss": 0, "Draw": 1}, "Coritiba": {"Win": 1, "Loss": 0, "Draw": 0}, "Avai": {"Win": 1, "Loss": 0, "Draw": 0}, "Sao Paulo": {"Win": 0, "Loss": 0, "Draw": 1}, "Palmeiras": {"Win": 1, "Loss": 0, "Draw": 0}, "Barueri": {"Win": 1, "Loss": 0, "Draw": 0}}, "Santo Andre": {"Botafogo-RJ": {"Win": 0, "Loss": 0, "Draw": 1}, "Flamengo": {"Win": 0, "Loss": 1, "Draw": 0}, "Santos": {"Win": 0, "Loss": 0, "Draw": 1}, "Sport": {"Win": 1, "Loss": 0, "Draw": 0}, "Barueri": {"Win": 0, "Loss": 0, "Draw": 1}, "Athletico-PR": {"Win": 1, "Loss": 0, "Draw": 0}, "Cruzeiro": {"Win": 0, "Loss": 1, "Draw": 0}, "Corinthians": {"Win": 0, "Loss": 0, "Draw": 1}, "Goias": {"Win": 0, "Loss": 1, "Draw": 0}, "Internacional": {"Win": 0, "Loss": 1, "Draw": 0}, "Coritiba": {"Win": 1, "Loss": 0, "Draw": 0}, "Atletico-MG": {"Win": 0, "Loss": 1, "Draw": 0}, "Sao Paulo": {"Win": 0, "Loss": 0, "Draw": 1}, "Vitoria": {"Win": 1, "Loss": 0, "Draw": 0}, "Fluminense": {"Win": 0, "Loss": 1, "Draw": 0}, "Palmeiras": {"Win": 1, "Loss": 0, "Draw": 0}, "Gremio": {"Win": 1, "Loss": 0, "Draw": 0}, "Avai": {"Win": 1, "Loss": 0, "Draw": 0}, "Nautico": {"Win": 1, "Loss": 0, "Draw": 0}}, "Goias": {"Nautico": {"Win": 0, "Loss": 0, "Draw": 1}, "Internacional": {"Win": 0, "Loss": 1, "Draw": 0}, "Corinthians": {"Win": 0, "Loss": 0, "Draw": 1}, "Barueri": {"Win": 0, "Loss": 0, "Draw": 1}, "Cruzeiro": {"Win": 1, "Loss": 0, "Draw": 0}, "Avai": {"Win": 0, "Loss": 1, "Draw": 0}, "Palmeiras": {"Win": 1, "Loss": 0, "Draw": 0}, "Athletico-PR": {"Win": 1, "Loss": 0, "Draw": 0}, "Flamengo": {"Win": 1, "Loss": 0, "Draw": 0}, "Vitoria": {"Win": 1, "Loss": 0, "Draw": 0}, "Santos": {"Win": 1, "Loss": 0, "Draw": 0}, "Coritiba": {"Win": 0, "Loss": 0, "Draw": 1}, "Gremio": {"Win": 1, "Loss": 0, "Draw": 0}, "Botafogo-RJ": {"Win": 0, "Loss": 1, "Draw": 0}, "Sport": {"Win": 0, "Loss": 0, "Draw": 1}, "Fluminense": {"Win": 0, "Loss": 0, "Draw": 1}, "Atletico-MG": {"Win": 0, "Loss": 1, "Draw": 0}, "Santo Andre": {"Win": 1, "Loss": 0, "Draw": 0}, "Sao Paulo": {"Win": 1, "Loss": 0, "Draw": 0}}, "Coritiba": {"Santo Andre": {"Win": 0, "Loss": 1, "Draw": 0}, "Goias": {"Win": 0, "Loss": 1, "Draw": 0}, "Flamengo": {"Win": 1, "Loss": 0, "Draw": 0}, "Sao Paulo": {"Win": 1, "Loss": 0, "Draw": 0}, "Gremio": {"Win": 1, "Loss": 0, "Draw": 0}, "Sport": {"Win": 0, "Loss": 0, "Draw": 1}, "Botafogo-RJ": {"Win": 0, "Loss": 0, "Draw": 1}, "Santos": {"Win": 0, "Loss": 1, "Draw": 0}, "Cruzeiro": {"Win": 0, "Loss": 1, "Draw": 0}, "Palmeiras": {"Win": 1, "Loss": 0, "Draw": 0}, "Avai": {"Win": 1, "Loss": 0, "Draw": 0}, "Corinthians": {"Win": 0, "Loss": 0, "Draw": 1}, "Nautico": {"Win": 1, "Loss": 0, "Draw": 0}, "Internacional": {"Win": 1, "Loss": 0, "Draw": 0}, "Barueri": {"Win": 0, "Loss": 1, "Draw": 0}, "Athletico-PR": {"Win": 1, "Loss": 0, "Draw": 0}, "Vitoria": {"Win": 1, "Loss": 0, "Draw": 0}, "Atletico-MG": {"Win": 1, "Loss": 0, "Draw": 0}, "Fluminense": {"Win": 0, "Loss": 0, "Draw": 1}}, "Atletico-MG": {"Gremio": {"Win": 1, "Loss": 0, "Draw": 0}, "Santo Andre": {"Win": 0, "Loss": 0, "Draw": 1}, "Nautico": {"Win": 1, "Loss": 0, "Draw": 0}, "Botafogo-RJ": {"Win": 0, "Loss": 0, "Draw": 1}, "Sao Paulo": {"Win": 1, "Loss": 0, "Draw": 0}, "Fluminense": {"Win": 1, "Loss": 0, "Draw": 0}, "Goias": {"Win": 0, "Loss": 1, "Draw": 0}, "Coritiba": {"Win": 1, "Loss": 0, "Draw": 0}, "Palmeiras": {"Win": 0, "Loss": 0, "Draw": 1}, "Avai": {"Win": 0, "Loss": 0, "Draw": 1}, "Sport": {"Win": 0, "Loss": 0, "Draw": 1}, "Athletico-PR": {"Win": 1, "Loss": 0, "Draw": 0}, "Santos": {"Win": 1, "Loss": 0, "Draw": 0}, "Barueri": {"Win": 1, "Loss": 0, "Draw": 0}, "Cruzeiro": {"Win": 0, "Loss": 1, "Draw": 0}, "Vitoria": {"Win": 1, "Loss": 0, "Draw": 0}, "Flamengo": {"Win": 0, "Loss": 1, "Draw": 0}, "Internacional": {"Win": 0, "Loss": 1, "Draw": 0}, "Corinthians": {"Win": 0, "Loss": 1, "Draw": 0}}, "Flamengo": {"Avai": {"Win": 0, "Loss": 0, "Draw": 1}, "Athletico-PR": {"Win": 1, "Loss": 0, "Draw": 0}, "Internacional": {"Win": 1, "Loss": 0, "Draw": 0}, "Vitoria": {"Win": 1, "Loss": 0, "Draw": 0}, "Palmeiras": {"Win": 0, "Loss": 1, "Draw": 0}, "Barueri": {"Win": 0, "Loss": 0, "Draw": 1}, "Atletico-MG": {"Win": 1, "Loss": 0, "Draw": 0}, "Nautico": {"Win": 0, "Loss": 0, "Draw": 1}, "Corinthians": {"Win": 1, "Loss": 0, "Draw": 0}, "Cruzeiro": {"Win": 0, "Loss": 1, "Draw": 0}, "Santo Andre": {"Win": 1, "Loss": 0, "Draw": 0}, "Sport": {"Win": 1, "Loss": 0, "Draw": 0}, "Coritiba": {"Win": 1, "Loss": 0, "Draw": 0}, "Fluminense": {"Win": 1, "Loss": 0, "Draw": 0}, "Sao Paulo": {"Win": 1, "Loss": 0, "Draw": 0}, "Santos": {"Win": 1, "Loss": 0, "Draw": 0}, "Goias": {"Win": 0, "Loss": 0, "Draw": 1}, "Gremio": {"Win": 1, "Loss": 0, "Draw": 0}}, "Santos": {"Goias": {"Win": 0, "Loss": 0, "Draw": 1}, "Corinthians": {"Win": 1, "Loss": 0, "Draw": 0}, "Atletico-MG": {"Win": 0, "Loss": 1, "Draw": 0}, "Sport": {"Win": 1, "Loss": 0, "Draw": 0}, "Barueri": {"Win": 0, "Loss": 0, "Draw": 1}, "Athletico-PR": {"Win": 1, "Loss": 0, "Draw": 0}, "Flamengo": {"Win": 0, "Loss": 1, "Draw": 0}, "Avai": {"Win": 0, "Loss": 0, "Draw": 1}, "Gremio": {"Win": 1, "Loss": 0, "Draw": 0}, "Internacional": {"Win": 0, "Loss": 0, "Draw": 1}, "Fluminense": {"Win": 1, "Loss": 0, "Draw": 0}, "Santo Andre": {"Win": 1, "Loss": 0, "Draw": 0}, "Botafogo-RJ": {"Win": 0, "Loss": 0, "Draw": 1}, "Palmeiras": {"Win": 0, "Loss": 1, "Draw": 0}, "Vitoria": {"Win": 0, "Loss": 0, "Draw": 1}, "Sao Paulo": {"Win": 0, "Loss": 1, "Draw": 0}, "Nautico": {"Win": 1, "Loss": 0, "Draw": 0}, "Coritiba": {"Win": 1, "Loss": 0, "Draw": 0}, "Cruzeiro": {"Win": 0, "Loss": 1, "Draw": 0}}, "Sao Paulo": {"Athletico-PR": {"Win": 0, "Loss": 0, "Draw": 1}, "Cruzeiro": {"Win": 1, "Loss": 0, "Draw": 0}, "Santo Andre": {"Win": 0, "Loss": 0, "Draw": 1}, "Nautico": {"Win": 1, "Loss": 0, "Draw": 0}, "Flamengo": {"Win": 0, "Loss": 0, "Draw": 1}, "Santos": {"Win": 1, "Loss": 0, "Draw": 0}, "Gremio": {"Win": 1, "Loss": 0, "Draw": 0}, "Botafogo-RJ": {"Win": 1, "Loss": 0, "Draw": 0}, "Goias": {"Win": 1, "Loss": 0, "Draw": 0}, "Fluminense": {"Win": 1, "Loss": 0, "Draw": 0}, "Palmeiras": {"Win": 0, "Loss": 0, "Draw": 1}, "Avai": {"Win": 1, "Loss": 0, "Draw": 0}, "Corinthians": {"Win": 0, "Loss": 0, "Draw": 1}, "Coritiba": {"Win": 0, "Loss": 0, "Draw": 1}, "Atletico-MG": {"Win": 0, "Loss": 1, "Draw": 0}, "Internacional": {"Win": 1, "Loss": 0, "Draw": 0}, "Barueri": {"Win": 1, "Loss": 0, "Draw": 0}, "Vitoria": {"Win": 1, "Loss": 0, "Draw": 0}, "Sport": {"Win": 1, "Loss": 0, "Draw": 0}}, "Barueri": {"Fluminense": {"Win": 0, "Loss": 0, "Draw": 1}, "Palmeiras": {"Win": 0, "Loss": 0, "Draw": 1}, "Avai": {"Win": 1, "Loss": 0, "Draw": 0}, "Atletico-MG": {"Win": 1, "Loss": 0, "Draw": 0}, "Coritiba": {"Win": 1, "Loss": 0, "Draw": 0}, "Nautico": {"Win": 1, "Loss": 0, "Draw": 0}, "Sao Paulo": {"Win": 0, "Loss": 1, "Draw": 0}, "Vitoria": {"Win": 1, "Loss": 0, "Draw": 0}, "Gremio": {"Win": 1, "Loss": 0, "Draw": 0}, "Sport": {"Win": 1, "Loss": 0, "Draw": 0}, "Corinthians": {"Win": 0, "Loss": 0, "Draw": 1}, "Goias": {"Win": 1, "Loss": 0, "Draw": 0}, "Cruzeiro": {"Win": 0, "Loss": 1, "Draw": 0}, "Santo Andre": {"Win": 0, "Loss": 0, "Draw": 1}, "Santos": {"Win": 0, "Loss": 0, "Draw": 1}, "Flamengo": {"Win": 1, "Loss": 0, "Draw": 0}, "Internacional": {"Win": 0, "Loss": 0, "Draw": 1}, "Botafogo-RJ": {"Win": 1, "Loss": 0, "Draw": 0}, "Athletico-PR": {"Win": 0, "Loss": 0, "Draw": 1}}, "Internacional": {"Palmeiras": {"Win": 1, "Loss": 0, "Draw": 0}, "Avai": {"Win": 1, "Loss": 0, "Draw": 0}, "Vitoria": {"Win": 0, "Loss": 0, "Draw": 1}, "Coritiba": {"Win": 1, "Loss": 0, "Draw": 0}, "Fluminense": {"Win": 1, "Loss": 0, "Draw": 0}, "Sao Paulo": {"Win": 0, "Loss": 0, "Draw": 1}, "Barueri": {"Win": 1, "Loss": 0, "Draw": 0}, "Sport": {"Win": 1, "Loss": 0, "Draw": 0}, "Corinthians": {"Win": 0, "Loss": 1, "Draw": 0}, "Goias": {"Win": 1, "Loss": 0, "Draw": 0}, "Atletico-MG": {"Win": 1, "Loss": 0, "Draw": 0}, "Cruzeiro": {"Win": 0, "Loss": 1, "Draw": 0}, "Flamengo": {"Win": 0, "Loss": 0, "Draw": 1}, "Nautico": {"Win": 1, "Loss": 0, "Draw": 0}, "Athletico-PR": {"Win": 0, "Loss": 0, "Draw": 1}, "Gremio": {"Win": 1, "Loss": 0, "Draw": 0}, "Botafogo-RJ": {"Win": 0, "Loss": 1, "Draw": 0}, "Santos": {"Win": 1, "Loss": 0, "Draw": 0}, "Santo Andre": {"Win": 1, "Loss": 0, "Draw": 0}}, "Botafogo-RJ": {"Corinthians": {"Win": 0, "Loss": 0, "Draw": 1}, "Sport": {"Win": 0, "Loss": 0, "Draw": 1}, "Santos": {"Win": 1, "Loss": 0, "Draw": 0}, "Goias": {"Win": 0, "Loss": 1, "Draw": 0}, "Flamengo": {"Win": 0, "Loss": 1, "Draw": 1}, "Internacional": {"Win": 1, "Loss": 0, "Draw": 0}, "Barueri": {"Win": 1, "Loss": 0, "Draw": 0}, "Athletico-PR": {"Win": 0, "Loss": 1, "Draw": 0}, "Santo Andre": {"Win": 0, "Loss": 1, "Draw": 0}, "Cruzeiro": {"Win": 0, "Loss": 0, "Draw": 1}, "Gremio": {"Win": 0, "Loss": 0, "Draw": 1}, "Fluminense": {"Win": 0, "Loss": 0, "Draw": 1}, "Vitoria": {"Win": 0, "Loss": 1, "Draw": 0}, "Atletico-MG": {"Win": 1, "Loss": 0, "Draw": 0}, "Avai": {"Win": 0, "Loss": 0, "Draw": 1}, "Nautico": {"Win": 1, "Loss": 0, "Draw": 0}, "Coritiba": {"Win": 1, "Loss": 0, "Draw": 0}, "Sao Paulo": {"Win": 1, "Loss": 0, "Draw": 0}, "Palmeiras": {"Win": 1, "Loss": 0, "Draw": 0}}, "Vitoria": {"Sport": {"Win": 1, "Loss": 0, "Draw": 0}, "Gremio": {"Win": 1, "Loss": 0, "Draw": 0}, "Botafogo-RJ": {"Win": 1, "Loss": 0, "Draw": 0}, "Santo Andre": {"Win": 1, "Loss": 0, "Draw": 0}, "Santos": {"Win": 1, "Loss": 0, "Draw": 0}, "Atletico-MG": {"Win": 0, "Loss": 0, "Draw": 1}, "Coritiba": {"Win": 1, "Loss": 0, "Draw": 0}, "Sao Paulo": {"Win": 0, "Loss": 1, "Draw": 0}, "Fluminense": {"Win": 0, "Loss": 0, "Draw": 1}, "Athletico-PR": {"Win": 1, "Loss": 0, "Draw": 0}, "Cruzeiro": {"Win": 0, "Loss": 0, "Draw": 1}, "Palmeiras": {"Win": 1, "Loss": 0, "Draw": 0}, "Internacional": {"Win": 1, "Loss": 0, "Draw": 0}, "Flamengo": {"Win": 0, "Loss": 0, "Draw": 1}, "Nautico": {"Win": 1, "Loss": 0, "Draw": 0}, "Corinthians": {"Win": 0, "Loss": 1, "Draw": 0}, "Avai": {"Win": 0, "Loss": 1, "Draw": 0}, "Barueri": {"Win": 1, "Loss": 0, "Draw": 0}, "Goias": {"Win": 0, "Loss": 0, "Draw": 1}}, "Nautico": {"Cruzeiro": {"Win": 1, "Loss": 0, "Draw": 0}, "Fluminense": {"Win": 0, "Loss": 0, "Draw": 1}, "Coritiba": {"Win": 0, "Loss": 1, "Draw": 0}, "Internacional": {"Win": 0, "Loss": 1, "Draw": 0}, "Vitoria": {"Win": 0, "Loss": 0, "Draw": 1}, "Botafogo-RJ": {"Win": 0, "Loss": 0, "Draw": 1}, "Santos": {"Win": 0, "Loss": 1, "Draw": 0}, "Corinthians": {"Win": 1, "Loss": 0, "Draw": 0}, "Santo Andre": {"Win": 1, "Loss": 0, "Draw": 0}, "Goias": {"Win": 1, "Loss": 0, "Draw": 0}, "Athletico-PR": {"Win": 1, "Loss": 0, "Draw": 0}, "Gremio": {"Win": 0, "Loss": 1, "Draw": 0}, "Atletico-MG": {"Win": 0, "Loss": 0, "Draw": 1}, "Sao Paulo": {"Win": 0, "Loss": 1, "Draw": 0}, "Palmeiras": {"Win": 1, "Loss": 0, "Draw": 0}, "Barueri": {"Win": 1, "Loss": 0, "Draw": 0}, "Sport": {"Win": 1, "Loss": 0, "Draw": 0}, "Flamengo": {"Win": 0, "Loss": 1, "Draw": 0}, "Avai": {"Win": 0, "Loss": 1, "Draw": 0}}}