{"Figueirense": {"Athletico-PR": {"Win": 0.0, "Draw": 1.0, "Loss": 0.0}, "Goias": {"Win": 0.0, "Draw": 0.0, "Loss": 1.0}, "Flamengo": {"Win": 0.0, "Draw": 0.0, "Loss": 1.0}, "Sao Paulo": {"Win": 0.0, "Draw": 0.0, "Loss": 1.0}, "Cruzeiro": {"Win": 0.5, "Draw": 0.0, "Loss": 0.5}, "Promoted": {"Win": 0.25, "Draw": 0.25, "Loss": 0.5}, "Sport": {"Win": 0.0, "Draw": 0.5, "Loss": 0.5}, "Corinthians": {"Win": 0.0, "Draw": 0.0, "Loss": 1.0}, "Gremio": {"Win": 0.5, "Draw": 0.5, "Loss": 0.0}, "Botafogo-RJ": {"Win": 0.5, "Draw": 0.5, "Loss": 0.0}, "Palmeiras": {"Win": 0.0, "Draw": 0.5, "Loss": 0.5}, "America-RN": {"Win": 1.0, "Draw": 0.0, "Loss": 0.0}, "Atletico-MG": {"Win": 0.0, "Draw": 0.5, "Loss": 0.5}, "Juventude": {"Win": 0.0, "Draw": 1.0, "Loss": 0.0}, "Internacional": {"Win": 0.0, "Draw": 0.5, "Loss": 0.5}, "Parana": {"Win": 1.0, "Draw": 0.0, "Loss": 0.0}, "Santos": {"Win": 0.0, "Draw": 0.0, "Loss": 1.0}, "Fluminense": {"Win": 0.0, "Draw": 0.5, "Loss": 0.5}, "Vasco": {"Win": 0.5, "Draw": 0.5, "Loss": 0.0}, "Nautico": {"Win": 0.5, "Draw": 0.0, "Loss": 0.5}, "Coritiba": {"Win": 0.0, "Draw": 0.0, "Loss": 1.0}, "Portuguesa": {"Win": 0.0, "Draw": 1.0, "Loss": 0.0}, "Vitoria": {"Win": 0.0, "Draw": 0.0, "Loss": 1.0}, "Ipatinga": {"Win": 1.0, "Draw": 0.0, "Loss": 0.0}}, "Sao Paulo": {"Goias": {"Win": 0.5, "Draw": 0.5, "Loss": 0.0}, "Palmeiras": {"Win": 0.5, "Draw": 0.5, "Loss": 0.0}, "Promoted": {"Win": 0.625, "Draw": 0.25, "Loss": 0.125}, "Atletico-MG": {"Win": 0.0, "Draw": 1.0, "Loss": 0.0}, "Vasco": {"Win": 1.0, "Draw": 0.0, "Loss": 0.0}, "Internacional": {"Win": 0.5, "Draw": 0.0, "Loss": 0.5}, "Flamengo": {"Win": 0.5, "Draw": 0.0, "Loss": 0.5}, "Fluminense": {"Win": 0.0, "Draw": 0.5, "Loss": 0.5}, "Sport": {"Win": 0.5, "Draw": 0.5, "Loss": 0.0}, "Juventude": {"Win": 0.0, "Draw": 0.0, "Loss": 1.0}, "Athletico-PR": {"Win": 0.0, "Draw": 0.5, "Loss": 0.5}, "Nautico": {"Win": 0.0, "Draw": 0.0, "Loss": 1.0}, "Parana": {"Win": 1.0, "Draw": 0.0, "Loss": 0.0}, "Santos": {"Win": 0.5, "Draw": 0.5, "Loss": 0.0}, "Figueirense": {"Win": 0.0, "Draw": 1.0, "Loss": 0.0}, "Corinthians": {"Win": 0.0, "Draw": 1.0, "Loss": 0.0}, "Cruzeiro": {"Win": 0.5, "Draw": 0.5, "Loss": 0.0}, "America-RN": {"Win": 1.0, "Draw": 0.0, "Loss": 0.0}, "Gremio": {"Win": 0.5, "Draw": 0.0, "Loss": 0.5}, "Botafogo-RJ": {"Win": 1.0, "Draw": 0.0, "Loss": 0.0}, "Coritiba": {"Win": 0.0, "Draw": 1.0, "Loss": 0.0}, "Ipatinga": {"Win": 1.0, "Draw": 0.0, "Loss": 0.0}, "Portuguesa": {"Win": 1.0, "Draw": 0.0, "Loss": 0.0}, "Vitoria": {"Win": 1.0, "Draw": 0.0, "Loss": 0.0}}, "Fluminense": {"Cruzeiro": {"Win": 0.0, "Draw": 0.0, "Loss": 1.0}, "Internacional": {"Win": 1.0, "Draw": 0.0, "Loss": 0.0}, "Promoted": {"Win": 0.25, "Draw": 0.25, "Loss": 0.5}, "Sport": {"Win": 0.5, "Draw": 0.0, "Loss": 0.5}, "Botafogo-RJ": {"Win": 0.5, "Draw": 0.5, "Loss": 0.0}, "Parana": {"Win": 0.0, "Draw": 0.0, "Loss": 1.0}, "Goias": {"Win": 0.0, "Draw": 0.0, "Loss": 1.0}, "Figueirense": {"Win": 1.0, "Draw": 0.0, "Loss": 0.0}, "Palmeiras": {"Win": 0.0, "Draw": 0.0, "Loss": 1.0}, "Santos": {"Win": 0.5, "Draw": 0.0, "Loss": 0.5}, "Flamengo": {"Win": 0.5, "Draw": 0.5, "Loss": 0.0}, "Gremio": {"Win": 0.0, "Draw": 0.0, "Loss": 1.0}, "Vasco": {"Win": 0.0, "Draw": 1.0, "Loss": 0.0}, "Athletico-PR": {"Win": 0.5, "Draw": 0.5, "Loss": 0.0}, "America-RN": {"Win": 1.0, "Draw": 0.0, "Loss": 0.0}, "Corinthians": {"Win": 0.0, "Draw": 1.0, "Loss": 0.0}, "Sao Paulo": {"Win": 0.5, "Draw": 0.5, "Loss": 0.0}, "Atletico-MG": {"Win": 0.0, "Draw": 0.5, "Loss": 0.5}, "Nautico": {"Win": 0.5, "Draw": 0.5, "Loss": 0.0}, "Juventude": {"Win": 0.0, "Draw": 1.0, "Loss": 0.0}, "Vitoria": {"Win": 0.0, "Draw": 1.0, "Loss": 0.0}, "Coritiba": {"Win": 0.0, "Draw": 0.0, "Loss": 1.0}, "Portuguesa": {"Win": 0.0, "Draw": 0.0, "Loss": 1.0}, "Ipatinga": {"Win": 0.0, "Draw": 0.0, "Loss": 1.0}}, "Flamengo": {"Palmeiras": {"Win": 0.0, "Draw": 0.0, "Loss": 1.0}, "Botafogo-RJ": {"Win": 0.5, "Draw": 0.5, "Loss": 0.0}, "Internacional": {"Win": 0.0, "Draw": 0.5, "Loss": 0.5}, "Parana": {"Win": 1.0, "Draw": 0.0, "Loss": 0.0}, "Promoted": {"Win": 0.25, "Draw": 0.5, "Loss": 0.25}, "America-RN": {"Win": 1.0, "Draw": 0.0, "Loss": 0.0}, "Nautico": {"Win": 0.5, "Draw": 0.0, "Loss": 0.5}, "Juventude": {"Win": 0.0, "Draw": 1.0, "Loss": 0.0}, "Goias": {"Win": 0.5, "Draw": 0.0, "Loss": 0.5}, "Sport": {"Win": 0.5, "Draw": 0.5, "Loss": 0.0}, "Figueirense": {"Win": 0.5, "Draw": 0.0, "Loss": 0.5}, "Cruzeiro": {"Win": 0.0, "Draw": 0.0, "Loss": 1.0}, "Vasco": {"Win": 1.0, "Draw": 0.0, "Loss": 0.0}, "Atletico-MG": {"Win": 0.0, "Draw": 1.0, "Loss": 0.0}, "Sao Paulo": {"Win": 0.0, "Draw": 0.5, "Loss": 0.5}, "Fluminense": {"Win": 1.0, "Draw": 0.0, "Loss": 0.0}, "Gremio": {"Win": 0.0, "Draw": 0.5, "Loss": 0.5}, "Corinthians": {"Win": 0.0, "Draw": 1.0, "Loss": 0.0}, "Santos": {"Win": 0.0, "Draw": 0.5, "Loss": 0.5}, "Athletico-PR": {"Win": 0.0, "Draw": 0.0, "Loss": 1.0}, "Vitoria": {"Win": 0.0, "Draw": 1.0, "Loss": 0.0}, "Ipatinga": {"Win": 1.0, "Draw": 0.0, "Loss": 0.0}, "Coritiba": {"Win": 0.0, "Draw": 0.0, "Loss": 1.0}, "Portuguesa": {"Win": 0.0, "Draw": 1.0, "Loss": 0.0}}, "Internacional": {"Botafogo-RJ": {"Win": 0.5, "Draw": 0.5, "Loss": 0.0}, "Promoted": {"Win": 0.25, "Draw": 0.25, "Loss": 0.5}, "Nautico": {"Win": 0.0, "Draw": 1.0, "Loss": 0.0}, "Santos": {"Win": 0.0, "Draw": 0.0, "Loss": 1.0}, "Gremio": {"Win": 0.0, "Draw": 0.5, "Loss": 0.5}, "Atletico-MG": {"Win": 0.0, "Draw": 1.0, "Loss": 0.0}, "Figueirense": {"Win": 0.0, "Draw": 0.5, "Loss": 0.5}, "Corinthians": {"Win": 0.0, "Draw": 1.0, "Loss": 0.0}, "Parana": {"Win": 0.0, "Draw": 0.0, "Loss": 1.0}, "Vasco": {"Win": 0.5, "Draw": 0.0, "Loss": 0.5}, "Goias": {"Win": 0.0, "Draw": 0.5, "Loss": 0.5}, "Athletico-PR": {"Win": 0.0, "Draw": 0.5, "Loss": 0.5}, "Fluminense": {"Win": 0.5, "Draw": 0.0, "Loss": 0.5}, "Flamengo": {"Win": 0.0, "Draw": 0.5, "Loss": 0.5}, "Sao Paulo": {"Win": 0.0, "Draw": 0.0, "Loss": 1.0}, "America-RN": {"Win": 1.0, "Draw": 0.0, "Loss": 0.0}, "Juventude": {"Win": 0.0, "Draw": 0.0, "Loss": 1.0}, "Sport": {"Win": 0.5, "Draw": 0.0, "Loss": 0.5}, "Cruzeiro": {"Win": 0.0, "Draw": 0.0, "Loss": 1.0}, "Palmeiras": {"Win": 0.0, "Draw": 0.5, "Loss": 0.5}, "Coritiba": {"Win": 0.0, "Draw": 0.0, "Loss": 1.0}, "Portuguesa": {"Win": 0.0, "Draw": 0.0, "Loss": 1.0}, "Vitoria": {"Win": 0.0, "Draw": 0.0, "Loss": 1.0}, "Ipatinga": {"Win": 0.0, "Draw": 0.0, "Loss": 1.0}}, "Parana": {"Gremio": {"Win": 0.0, "Draw": 0.0, "Loss": 1.0}, "Sao Paulo": {"Win": 0.0, "Draw": 0.0, "Loss": 1.0}, "Promoted": {"Win": 0.0, "Draw": 0.5, "Loss": 0.5}, "Sport": {"Win": 0.0, "Draw": 0.0, "Loss": 1.0}, "Athletico-PR": {"Win": 0.0, "Draw": 0.0, "Loss": 1.0}, "America-RN": {"Win": 0.0, "Draw": 0.0, "Loss": 1.0}, "Figueirense": {"Win": 0.0, "Draw": 0.0, "Loss": 1.0}, "Palmeiras": {"Win": 0.0, "Draw": 0.0, "Loss": 1.0}, "Atletico-MG": {"Win": 0.0, "Draw": 1.0, "Loss": 0.0}, "Botafogo-RJ": {"Win": 0.0, "Draw": 0.0, "Loss": 1.0}, "Vasco": {"Win": 0.0, "Draw": 0.0, "Loss": 1.0}, "Juventude": {"Win": 1.0, "Draw": 0.0, "Loss": 0.0}, "Cruzeiro": {"Win": 1.0, "Draw": 0.0, "Loss": 0.0}, "Nautico": {"Win": 0.0, "Draw": 1.0, "Loss": 0.0}, "Corinthians": {"Win": 0.0, "Draw": 1.0, "Loss": 0.0}, "Fluminense": {"Win": 0.0, "Draw": 1.0, "Loss": 0.0}, "Flamengo": {"Win": 1.0, "Draw": 0.0, "Loss": 0.0}, "Internacional": {"Win": 0.0, "Draw": 0.0, "Loss": 1.0}, "Goias": {"Win": 0.0, "Draw": 0.0, "Loss": 1.0}, "Santos": {"Win": 0.0, "Draw": 0.0, "Loss": 1.0}}, "Promoted": {"Nautico": {"Win": 0.2857142857142857, "Draw": 0.14285714285714285, "Loss": 0.5714285714285714}, "Athletico-PR": {"Win": 0.0, "Draw": 0.375, "Loss": 0.625}, "Figueirense": {"Win": 0.25, "Draw": 0.125, "Loss": 0.625}, "Flamengo": {"Win": 0.125, "Draw": 0.25, "Loss": 0.625}, "Gremio": {"Win": 0.0, "Draw": 0.125, "Loss": 0.875}, "America-RN": {"Win": 0.6666666666666666, "Draw": 0.3333333333333333, "Loss": 0.0}, "Fluminense": {"Win": 0.125, "Draw": 0.25, "Loss": 0.625}, "Santos": {"Win": 0.375, "Draw": 0.25, "Loss": 0.375}, "Palmeiras": {"Win": 0.25, "Draw": 0.0, "Loss": 0.75}, "Botafogo-RJ": {"Win": 0.125, "Draw": 0.0, "Loss": 0.875}, "Corinthians": {"Win": 0.5, "Draw": 0.25, "Loss": 0.25}, "Sao Paulo": {"Win": 0.125, "Draw": 0.25, "Loss": 0.625}, "Cruzeiro": {"Win": 0.0, "Draw": 0.25, "Loss": 0.75}, "Internacional": {"Win": 0.0, "Draw": 0.25, "Loss": 0.75}, "Sport": {"Win": 0.0, "Draw": 0.2857142857142857, "Loss": 0.7142857142857143}, "Vasco": {"Win": 0.25, "Draw": 0.0, "Loss": 0.75}, "Parana": {"Win": 0.75, "Draw": 0.0, "Loss": 0.25}, "Juventude": {"Win": 0.25, "Draw": 0.25, "Loss": 0.5}, "Goias": {"Win": 0.125, "Draw": 0.375, "Loss": 0.5}, "Atletico-MG": {"Win": 0.0, "Draw": 0.0, "Loss": 1.0}, "Ipatinga": {"Win": 0.0, "Draw": 0.0, "Loss": 1.0}, "Coritiba": {"Win": 0.0, "Draw": 0.3333333333333333, "Loss": 0.6666666666666666}, "Portuguesa": {"Win": 0.3333333333333333, "Draw": 0.3333333333333333, "Loss": 0.3333333333333333}, "Vitoria": {"Win": 0.0, "Draw": 0.3333333333333333, "Loss": 0.6666666666666666}}, "Atletico-MG": {"Nautico": {"Win": 0.5, "Draw": 0.0, "Loss": 0.5}, "Athletico-PR": {"Win": 0.0, "Draw": 0.5, "Loss": 0.5}, "Figueirense": {"Win": 0.0, "Draw": 0.5, "Loss": 0.5}, "Flamengo": {"Win": 0.5, "Draw": 0.0, "Loss": 0.5}, "Gremio": {"Win": 0.0, "Draw": 0.5, "Loss": 0.5}, "America-RN": {"Win": 1.0, "Draw": 0.0, "Loss": 0.0}, "Fluminense": {"Win": 0.0, "Draw": 0.5, "Loss": 0.5}, "Santos": {"Win": 0.5, "Draw": 0.5, "Loss": 0.0}, "Palmeiras": {"Win": 0.5, "Draw": 0.0, "Loss": 0.5}, "Botafogo-RJ": {"Win": 0.0, "Draw": 0.0, "Loss": 1.0}, "Corinthians": {"Win": 0.0, "Draw": 1.0, "Loss": 0.0}, "Sao Paulo": {"Win": 0.5, "Draw": 0.0, "Loss": 0.5}, "Cruzeiro": {"Win": 0.0, "Draw": 0.0, "Loss": 1.0}, "Internacional": {"Win": 0.0, "Draw": 0.5, "Loss": 0.5}, "Sport": {"Win": 0.0, "Draw": 0.0, "Loss": 1.0}, "Vasco": {"Win": 0.0, "Draw": 0.0, "Loss": 1.0}, "Parana": {"Win": 1.0, "Draw": 0.0, "Loss": 0.0}, "Juventude": {"Win": 1.0, "Draw": 0.0, "Loss": 0.0}, "Goias": {"Win": 0.0, "Draw": 0.5, "Loss": 0.5}, "Promoted": {"Win": 0.25, "Draw": 0.25, "Loss": 0.5}, "Portuguesa": {"Win": 0.0, "Draw": 1.0, "Loss": 0.0}, "Ipatinga": {"Win": 0.0, "Draw": 0.0, "Loss": 1.0}, "Coritiba": {"Win": 0.0, "Draw": 0.0, "Loss": 1.0}, "Vitoria": {"Win": 1.0, "Draw": 0.0, "Loss": 0.0}}, "Corinthians": {"Juventude": {"Win": 0.0, "Draw": 1.0, "Loss": 0.0}, "Promoted": {"Win": 0.25, "Draw": 0.0, "Loss": 0.75}, "Atletico-MG": {"Win": 0.0, "Draw": 0.0, "Loss": 1.0}, "Parana": {"Win": 0.0, "Draw": 0.0, "Loss": 1.0}, "Palmeiras": {"Win": 0.0, "Draw": 0.0, "Loss": 1.0}, "Fluminense": {"Win": 0.0, "Draw": 1.0, "Loss": 0.0}, "Sao Paulo": {"Win": 1.0, "Draw": 0.0, "Loss": 0.0}, "Nautico": {"Win": 0.0, "Draw": 0.0, "Loss": 1.0}, "Flamengo": {"Win": 0.0, "Draw": 0.0, "Loss": 1.0}, "Goias": {"Win": 0.0, "Draw": 1.0, "Loss": 0.0}, "Gremio": {"Win": 0.0, "Draw": 1.0, "Loss": 0.0}, "Cruzeiro": {"Win": 1.0, "Draw": 0.0, "Loss": 0.0}, "Santos": {"Win": 0.0, "Draw": 1.0, "Loss": 0.0}, "America-RN": {"Win": 1.0, "Draw": 0.0, "Loss": 0.0}, "Botafogo-RJ": {"Win": 1.0, "Draw": 0.0, "Loss": 0.0}, "Sport": {"Win": 0.0, "Draw": 0.0, "Loss": 1.0}, "Internacional": {"Win": 0.0, "Draw": 0.0, "Loss": 1.0}, "Figueirense": {"Win": 0.0, "Draw": 1.0, "Loss": 0.0}, "Athletico-PR": {"Win": 0.0, "Draw": 1.0, "Loss": 0.0}, "Vasco": {"Win": 0.0, "Draw": 0.0, "Loss": 1.0}}, "America-RN": {"Vasco": {"Win": 0.0, "Draw": 0.0, "Loss": 1.0}, "Figueirense": {"Win": 0.0, "Draw": 0.0, "Loss": 1.0}, "Corinthians": {"Win": 0.0, "Draw": 0.0, "Loss": 1.0}, "Fluminense": {"Win": 0.0, "Draw": 0.0, "Loss": 1.0}, "Goias": {"Win": 0.0, "Draw": 1.0, "Loss": 0.0}, "Internacional": {"Win": 0.0, "Draw": 0.0, "Loss": 1.0}, "Athletico-PR": {"Win": 0.0, "Draw": 0.0, "Loss": 1.0}, "Sao Paulo": {"Win": 0.0, "Draw": 0.0, "Loss": 1.0}, "Nautico": {"Win": 0.0, "Draw": 0.0, "Loss": 1.0}, "Cruzeiro": {"Win": 0.0, "Draw": 0.0, "Loss": 1.0}, "Santos": {"Win": 1.0, "Draw": 0.0, "Loss": 0.0}, "Juventude": {"Win": 0.0, "Draw": 0.0, "Loss": 1.0}, "Sport": {"Win": 0.0, "Draw": 1.0, "Loss": 0.0}, "Palmeiras": {"Win": 0.0, "Draw": 0.0, "Loss": 1.0}, "Parana": {"Win": 1.0, "Draw": 0.0, "Loss": 0.0}, "Atletico-MG": {"Win": 0.0, "Draw": 0.0, "Loss": 1.0}, "Flamengo": {"Win": 0.0, "Draw": 0.0, "Loss": 1.0}, "Botafogo-RJ": {"Win": 0.0, "Draw": 0.0, "Loss": 1.0}, "Gremio": {"Win": 0.0, "Draw": 0.0, "Loss": 1.0}}, "Sport": {"Santos": {"Win": 0.0, "Draw": 0.0, "Loss": 1.0}, "Flamengo": {"Win": 0.0, "Draw": 0.5, "Loss": 0.5}, "America-RN": {"Win": 0.0, "Draw": 1.0, "Loss": 0.0}, "Nautico": {"Win": 0.5, "Draw": 0.0, "Loss": 0.5}, "Corinthians": {"Win": 1.0, "Draw": 0.0, "Loss": 0.0}, "Atletico-MG": {"Win": 0.0, "Draw": 0.0, "Loss": 1.0}, "Botafogo-RJ": {"Win": 0.0, "Draw": 0.0, "Loss": 1.0}, "Internacional": {"Win": 0.0, "Draw": 1.0, "Loss": 0.0}, "Athletico-PR": {"Win": 0.0, "Draw": 0.5, "Loss": 0.5}, "Juventude": {"Win": 0.0, "Draw": 0.0, "Loss": 1.0}, "Vasco": {"Win": 0.0, "Draw": 0.0, "Loss": 1.0}, "Gremio": {"Win": 0.0, "Draw": 0.0, "Loss": 1.0}, "Fluminense": {"Win": 0.0, "Draw": 0.5, "Loss": 0.5}, "Parana": {"Win": 0.0, "Draw": 0.0, "Loss": 1.0}, "Goias": {"Win": 0.5, "Draw": 0.0, "Loss": 0.5}, "Figueirense": {"Win": 0.5, "Draw": 0.0, "Loss": 0.5}, "Sao Paulo": {"Win": 0.0, "Draw": 0.0, "Loss": 1.0}, "Palmeiras": {"Win": 1.0, "Draw": 0.0, "Loss": 0.0}, "Cruzeiro": {"Win": 0.0, "Draw": 0.0, "Loss": 1.0}, "Promoted": {"Win": 0.0, "Draw": 0.5, "Loss": 0.5}, "Vitoria": {"Win": 0.0, "Draw": 1.0, "Loss": 0.0}, "Ipatinga": {"Win": 0.0, "Draw": 0.0, "Loss": 1.0}, "Portuguesa": {"Win": 0.0, "Draw": 1.0, "Loss": 0.0}, "Coritiba": {"Win": 0.0, "Draw": 0.0, "Loss": 1.0}}, "Juventude": {"Parana": {"Win": 0.0, "Draw": 0.0, "Loss": 1.0}, "Promoted": {"Win": 0.25, "Draw": 0.0, "Loss": 0.75}, "America-RN": {"Win": 1.0, "Draw": 0.0, "Loss": 0.0}, "Santos": {"Win": 0.0, "Draw": 0.0, "Loss": 1.0}, "Figueirense": {"Win": 0.0, "Draw": 0.0, "Loss": 1.0}, "Vasco": {"Win": 1.0, "Draw": 0.0, "Loss": 0.0}, "Nautico": {"Win": 0.0, "Draw": 0.0, "Loss": 1.0}, "Internacional": {"Win": 0.0, "Draw": 0.0, "Loss": 1.0}, "Palmeiras": {"Win": 1.0, "Draw": 0.0, "Loss": 0.0}, "Atletico-MG": {"Win": 0.0, "Draw": 0.0, "Loss": 1.0}, "Fluminense": {"Win": 0.0, "Draw": 0.0, "Loss": 1.0}, "Corinthians": {"Win": 0.0, "Draw": 0.0, "Loss": 1.0}, "Goias": {"Win": 0.0, "Draw": 0.0, "Loss": 1.0}, "Cruzeiro": {"Win": 1.0, "Draw": 0.0, "Loss": 0.0}, "Flamengo": {"Win": 0.0, "Draw": 0.0, "Loss": 1.0}, "Gremio": {"Win": 0.0, "Draw": 0.0, "Loss": 1.0}, "Athletico-PR": {"Win": 0.0, "Draw": 0.0, "Loss": 1.0}, "Botafogo-RJ": {"Win": 0.0, "Draw": 0.0, "Loss": 1.0}, "Sao Paulo": {"Win": 0.0, "Draw": 0.0, "Loss": 1.0}, "Sport": {"Win": 0.0, "Draw": 0.0, "Loss": 1.0}}, "Athletico-PR": {"Internacional": {"Win": 0.0, "Draw": 0.0, "Loss": 1.0}, "Santos": {"Win": 0.0, "Draw": 0.0, "Loss": 1.0}, "Goias": {"Win": 0.5, "Draw": 0.0, "Loss": 0.5}, "Fluminense": {"Win": 0.0, "Draw": 0.0, "Loss": 1.0}, "Promoted": {"Win": 0.125, "Draw": 0.25, "Loss": 0.625}, "Nautico": {"Win": 0.0, "Draw": 0.0, "Loss": 1.0}, "Juventude": {"Win": 0.0, "Draw": 1.0, "Loss": 0.0}, "Cruzeiro": {"Win": 0.0, "Draw": 0.5, "Loss": 0.5}, "Corinthians": {"Win": 0.0, "Draw": 1.0, "Loss": 0.0}, "Flamengo": {"Win": 0.0, "Draw": 0.0, "Loss": 1.0}, "Figueirense": {"Win": 1.0, "Draw": 0.0, "Loss": 0.0}, "Atletico-MG": {"Win": 0.0, "Draw": 0.5, "Loss": 0.5}, "Palmeiras": {"Win": 0.5, "Draw": 0.0, "Loss": 0.5}, "Parana": {"Win": 0.0, "Draw": 1.0, "Loss": 0.0}, "Botafogo-RJ": {"Win": 0.0, "Draw": 0.5, "Loss": 0.5}, "Vasco": {"Win": 0.0, "Draw": 0.5, "Loss": 0.5}, "America-RN": {"Win": 0.0, "Draw": 0.0, "Loss": 1.0}, "Gremio": {"Win": 0.0, "Draw": 0.5, "Loss": 0.5}, "Sport": {"Win": 0.0, "Draw": 0.0, "Loss": 1.0}, "Sao Paulo": {"Win": 0.0, "Draw": 0.0, "Loss": 1.0}, "Coritiba": {"Win": 0.0, "Draw": 1.0, "Loss": 0.0}, "Ipatinga": {"Win": 1.0, "Draw": 0.0, "Loss": 0.0}, "Portuguesa": {"Win": 0.0, "Draw": 0.0, "Loss": 1.0}, "Vitoria": {"Win": 0.0, "Draw": 0.0, "Loss": 1.0}}, "Santos": {"Promoted": {"Win": 0.375, "Draw": 0.25, "Loss": 0.375}, "America-RN": {"Win": 1.0, "Draw": 0.0, "Loss": 0.0}, "Corinthians": {"Win": 0.0, "Draw": 0.0, "Loss": 1.0}, "Sao Paulo": {"Win": 0.0, "Draw": 0.5, "Loss": 0.5}, "Gremio": {"Win": 0.0, "Draw": 0.0, "Loss": 1.0}, "Cruzeiro": {"Win": 0.5, "Draw": 0.0, "Loss": 0.5}, "Botafogo-RJ": {"Win": 1.0, "Draw": 0.0, "Loss": 0.0}, "Figueirense": {"Win": 0.0, "Draw": 0.0, "Loss": 1.0}, "Nautico": {"Win": 0.5, "Draw": 0.0, "Loss": 0.5}, "Flamengo": {"Win": 0.0, "Draw": 0.0, "Loss": 1.0}, "Parana": {"Win": 1.0, "Draw": 0.0, "Loss": 0.0}, "Sport": {"Win": 0.0, "Draw": 0.5, "Loss": 0.5}, "Athletico-PR": {"Win": 0.5, "Draw": 0.0, "Loss": 0.5}, "Internacional": {"Win": 0.5, "Draw": 0.0, "Loss": 0.5}, "Juventude": {"Win": 1.0, "Draw": 0.0, "Loss": 0.0}, "Vasco": {"Win": 0.0, "Draw": 0.0, "Loss": 1.0}, "Palmeiras": {"Win": 0.0, "Draw": 0.5, "Loss": 0.5}, "Goias": {"Win": 0.0, "Draw": 0.0, "Loss": 1.0}, "Atletico-MG": {"Win": 0.5, "Draw": 0.5, "Loss": 0.0}, "Fluminense": {"Win": 0.0, "Draw": 0.5, "Loss": 0.5}, "Ipatinga": {"Win": 0.0, "Draw": 1.0, "Loss": 0.0}, "Coritiba": {"Win": 0.0, "Draw": 0.0, "Loss": 1.0}, "Vitoria": {"Win": 0.0, "Draw": 0.0, "Loss": 1.0}, "Portuguesa": {"Win": 0.0, "Draw": 1.0, "Loss": 0.0}}, "Cruzeiro": {"Corinthians": {"Win": 1.0, "Draw": 0.0, "Loss": 0.0}, "Parana": {"Win": 0.0, "Draw": 1.0, "Loss": 0.0}, "Juventude": {"Win": 0.0, "Draw": 0.0, "Loss": 1.0}, "Promoted": {"Win": 0.5, "Draw": 0.25, "Loss": 0.25}, "Atletico-MG": {"Win": 1.0, "Draw": 0.0, "Loss": 0.0}, "Vasco": {"Win": 1.0, "Draw": 0.0, "Loss": 0.0}, "Goias": {"Win": 0.0, "Draw": 0.5, "Loss": 0.5}, "Sao Paulo": {"Win": 0.0, "Draw": 0.0, "Loss": 1.0}, "Botafogo-RJ": {"Win": 0.0, "Draw": 0.0, "Loss": 1.0}, "Internacional": {"Win": 0.0, "Draw": 0.0, "Loss": 1.0}, "Sport": {"Win": 0.0, "Draw": 0.0, "Loss": 1.0}, "Fluminense": {"Win": 0.5, "Draw": 0.5, "Loss": 0.0}, "Palmeiras": {"Win": 0.5, "Draw": 0.0, "Loss": 0.5}, "Gremio": {"Win": 0.5, "Draw": 0.0, "Loss": 0.5}, "Figueirense": {"Win": 0.5, "Draw": 0.0, "Loss": 0.5}, "Santos": {"Win": 0.0, "Draw": 0.0, "Loss": 1.0}, "Nautico": {"Win": 0.5, "Draw": 0.0, "Loss": 0.5}, "Athletico-PR": {"Win": 0.0, "Draw": 0.5, "Loss": 0.5}, "Flamengo": {"Win": 0.5, "Draw": 0.0, "Loss": 0.5}, "America-RN": {"Win": 1.0, "Draw": 0.0, "Loss": 0.0}, "Vitoria": {"Win": 1.0, "Draw": 0.0, "Loss": 0.0}, "Coritiba": {"Win": 0.0, "Draw": 1.0, "Loss": 0.0}, "Ipatinga": {"Win": 0.0, "Draw": 1.0, "Loss": 0.0}, "Portuguesa": {"Win": 0.0, "Draw": 0.0, "Loss": 1.0}}, "Goias": {"Flamengo": {"Win": 0.0, "Draw": 0.5, "Loss": 0.5}, "Juventude": {"Win": 0.0, "Draw": 0.0, "Loss": 1.0}, "Palmeiras": {"Win": 0.0, "Draw": 0.0, "Loss": 1.0}, "Botafogo-RJ": {"Win": 0.5, "Draw": 0.0, "Loss": 0.5}, "Promoted": {"Win": 0.25, "Draw": 0.25, "Loss": 0.5}, "Sport": {"Win": 0.0, "Draw": 0.0, "Loss": 1.0}, "Gremio": {"Win": 0.5, "Draw": 0.0, "Loss": 0.5}, "Santos": {"Win": 0.5, "Draw": 0.0, "Loss": 0.5}, "Parana": {"Win": 0.0, "Draw": 0.0, "Loss": 1.0}, "Atletico-MG": {"Win": 0.0, "Draw": 0.5, "Loss": 0.5}, "Sao Paulo": {"Win": 0.0, "Draw": 0.0, "Loss": 1.0}, "Figueirense": {"Win": 0.0, "Draw": 0.5, "Loss": 0.5}, "Athletico-PR": {"Win": 0.5, "Draw": 0.0, "Loss": 0.5}, "Nautico": {"Win": 0.5, "Draw": 0.0, "Loss": 0.5}, "America-RN": {"Win": 1.0, "Draw": 0.0, "Loss": 0.0}, "Cruzeiro": {"Win": 0.5, "Draw": 0.0, "Loss": 0.5}, "Fluminense": {"Win": 0.0, "Draw": 0.5, "Loss": 0.5}, "Vasco": {"Win": 0.0, "Draw": 0.5, "Loss": 0.5}, "Corinthians": {"Win": 0.0, "Draw": 0.0, "Loss": 1.0}, "Internacional": {"Win": 0.0, "Draw": 0.0, "Loss": 1.0}, "Ipatinga": {"Win": 0.0, "Draw": 0.0, "Loss": 1.0}, "Coritiba": {"Win": 0.0, "Draw": 1.0, "Loss": 0.0}, "Portuguesa": {"Win": 0.0, "Draw": 1.0, "Loss": 0.0}, "Vitoria": {"Win": 0.0, "Draw": 0.0, "Loss": 1.0}}, "Palmeiras": {"Figueirense": {"Win": 0.5, "Draw": 0.5, "Loss": 0.0}, "Cruzeiro": {"Win": 0.5, "Draw": 0.0, "Loss": 0.5}, "Botafogo-RJ": {"Win": 0.0, "Draw": 0.5, "Loss": 0.5}, "Athletico-PR": {"Win": 0.5, "Draw": 0.0, "Loss": 0.5}, "Promoted": {"Win": 0.375, "Draw": 0.375, "Loss": 0.25}, "America-RN": {"Win": 0.0, "Draw": 1.0, "Loss": 0.0}, "Santos": {"Win": 0.5, "Draw": 0.5, "Loss": 0.0}, "Vasco": {"Win": 0.5, "Draw": 0.5, "Loss": 0.0}, "Sport": {"Win": 0.0, "Draw": 0.0, "Loss": 1.0}, "Internacional": {"Win": 0.0, "Draw": 0.0, "Loss": 1.0}, "Flamengo": {"Win": 0.5, "Draw": 0.0, "Loss": 0.5}, "Sao Paulo": {"Win": 0.0, "Draw": 0.5, "Loss": 0.5}, "Goias": {"Win": 0.0, "Draw": 0.0, "Loss": 1.0}, "Corinthians": {"Win": 1.0, "Draw": 0.0, "Loss": 0.0}, "Nautico": {"Win": 0.5, "Draw": 0.5, "Loss": 0.0}, "Gremio": {"Win": 0.0, "Draw": 1.0, "Loss": 0.0}, "Parana": {"Win": 0.0, "Draw": 0.0, "Loss": 1.0}, "Juventude": {"Win": 0.0, "Draw": 1.0, "Loss": 0.0}, "Fluminense": {"Win": 0.5, "Draw": 0.0, "Loss": 0.5}, "Atletico-MG": {"Win": 0.5, "Draw": 0.5, "Loss": 0.0}, "Vitoria": {"Win": 0.0, "Draw": 1.0, "Loss": 0.0}, "Coritiba": {"Win": 0.0, "Draw": 0.0, "Loss": 1.0}, "Portuguesa": {"Win": 0.0, "Draw": 1.0, "Loss": 0.0}, "Ipatinga": {"Win": 1.0, "Draw": 0.0, "Loss": 0.0}}, "Botafogo-RJ": {"Promoted": {"Win": 0.375, "Draw": 0.25, "Loss": 0.375}, "Atletico-MG": {"Win": 0.5, "Draw": 0.0, "Loss": 0.5}, "Gremio": {"Win": 0.0, "Draw": 0.0, "Loss": 1.0}, "Vasco": {"Win": 0.0, "Draw": 0.5, "Loss": 0.5}, "Nautico": {"Win": 0.0, "Draw": 0.0, "Loss": 1.0}, "Athletico-PR": {"Win": 0.5, "Draw": 0.0, "Loss": 0.5}, "Juventude": {"Win": 0.0, "Draw": 1.0, "Loss": 0.0}, "America-RN": {"Win": 0.0, "Draw": 1.0, "Loss": 0.0}, "Sao Paulo": {"Win": 0.0, "Draw": 0.5, "Loss": 0.5}, "Corinthians": {"Win": 1.0, "Draw": 0.0, "Loss": 0.0}, "Internacional": {"Win": 0.5, "Draw": 0.0, "Loss": 0.5}, "Flamengo": {"Win": 0.0, "Draw": 1.0, "Loss": 0.0}, "Palmeiras": {"Win": 0.5, "Draw": 0.5, "Loss": 0.0}, "Fluminense": {"Win": 0.5, "Draw": 0.5, "Loss": 0.0}, "Goias": {"Win": 0.0, "Draw": 0.5, "Loss": 0.5}, "Santos": {"Win": 0.0, "Draw": 0.5, "Loss": 0.5}, "Sport": {"Win": 0.5, "Draw": 0.5, "Loss": 0.0}, "Cruzeiro": {"Win": 0.0, "Draw": 0.0, "Loss": 1.0}, "Parana": {"Win": 0.0, "Draw": 1.0, "Loss": 0.0}, "Figueirense": {"Win": 0.5, "Draw": 0.5, "Loss": 0.0}, "Coritiba": {"Win": 1.0, "Draw": 0.0, "Loss": 0.0}, "Portuguesa": {"Win": 0.0, "Draw": 0.0, "Loss": 1.0}, "Ipatinga": {"Win": 1.0, "Draw": 0.0, "Loss": 0.0}, "Vitoria": {"Win": 0.0, "Draw": 0.0, "Loss": 1.0}}, "Gremio": {"Fluminense": {"Win": 0.0, "Draw": 1.0, "Loss": 0.0}, "Promoted": {"Win": 0.625, "Draw": 0.0, "Loss": 0.375}, "Sport": {"Win": 0.0, "Draw": 0.5, "Loss": 0.5}, "Cruzeiro": {"Win": 0.0, "Draw": 0.0, "Loss": 1.0}, "Juventude": {"Win": 1.0, "Draw": 0.0, "Loss": 0.0}, "Palmeiras": {"Win": 0.5, "Draw": 0.0, "Loss": 0.5}, "Flamengo": {"Win": 0.0, "Draw": 0.0, "Loss": 1.0}, "Athletico-PR": {"Win": 0.0, "Draw": 0.5, "Loss": 0.5}, "Sao Paulo": {"Win": 0.5, "Draw": 0.0, "Loss": 0.5}, "America-RN": {"Win": 1.0, "Draw": 0.0, "Loss": 0.0}, "Parana": {"Win": 0.0, "Draw": 0.0, "Loss": 1.0}, "Botafogo-RJ": {"Win": 0.0, "Draw": 0.0, "Loss": 1.0}, "Vasco": {"Win": 0.0, "Draw": 0.0, "Loss": 1.0}, "Internacional": {"Win": 0.5, "Draw": 0.0, "Loss": 0.5}, "Santos": {"Win": 0.0, "Draw": 1.0, "Loss": 0.0}, "Atletico-MG": {"Win": 1.0, "Draw": 0.0, "Loss": 0.0}, "Goias": {"Win": 0.5, "Draw": 0.5, "Loss": 0.0}, "Nautico": {"Win": 0.5, "Draw": 0.5, "Loss": 0.0}, "Figueirense": {"Win": 0.5, "Draw": 0.0, "Loss": 0.5}, "Corinthians": {"Win": 0.0, "Draw": 0.0, "Loss": 1.0}, "Portuguesa": {"Win": 0.0, "Draw": 0.0, "Loss": 1.0}, "Vitoria": {"Win": 0.0, "Draw": 0.0, "Loss": 1.0}, "Ipatinga": {"Win": 1.0, "Draw": 0.0, "Loss": 0.0}, "Coritiba": {"Win": 1.0, "Draw": 0.0, "Loss": 0.0}}, "Nautico": {"Sao Paulo": {"Win": 0.0, "Draw": 0.0, "Loss": 1.0}, "Vasco": {"Win": 0.5, "Draw": 0.0, "Loss": 0.5}, "Parana": {"Win": 1.0, "Draw": 0.0, "Loss": 0.0}, "Goias": {"Win": 0.5, "Draw": 0.0, "Loss": 0.5}, "Palmeiras": {"Win": 0.0, "Draw": 0.0, "Loss": 1.0}, "Cruzeiro": {"Win": 0.0, "Draw": 0.5, "Loss": 0.5}, "Gremio": {"Win": 0.0, "Draw": 0.0, "Loss": 1.0}, "Fluminense": {"Win": 0.5, "Draw": 0.0, "Loss": 0.5}, "Figueirense": {"Win": 0.0, "Draw": 0.0, "Loss": 1.0}, "Atletico-MG": {"Win": 0.0, "Draw": 0.0, "Loss": 1.0}, "Internacional": {"Win": 0.0, "Draw": 0.5, "Loss": 0.5}, "Botafogo-RJ": {"Win": 0.0, "Draw": 0.5, "Loss": 0.5}, "Sport": {"Win": 0.0, "Draw": 0.5, "Loss": 0.5}, "Athletico-PR": {"Win": 0.0, "Draw": 0.5, "Loss": 0.5}, "Juventude": {"Win": 0.0, "Draw": 1.0, "Loss": 0.0}, "Corinthians": {"Win": 1.0, "Draw": 0.0, "Loss": 0.0}, "Santos": {"Win": 0.5, "Draw": 0.5, "Loss": 0.0}, "America-RN": {"Win": 1.0, "Draw": 0.0, "Loss": 0.0}, "Flamengo": {"Win": 0.0, "Draw": 0.0, "Loss": 1.0}, "Promoted": {"Win": 0.0, "Draw": 0.5, "Loss": 0.5}, "Coritiba": {"Win": 0.0, "Draw": 1.0, "Loss": 0.0}, "Ipatinga": {"Win": 0.0, "Draw": 1.0, "Loss": 0.0}, "Portuguesa": {"Win": 0.0, "Draw": 0.0, "Loss": 1.0}, "Vitoria": {"Win": 0.0, "Draw": 0.0, "Loss": 1.0}}, "Vasco": {"Promoted": {"Win": 0.375, "Draw": 0.25, "Loss": 0.375}, "Sport": {"Win": 0.0, "Draw": 1.0, "Loss": 0.0}, "Fluminense": {"Win": 0.5, "Draw": 0.5, "Loss": 0.0}, "Gremio": {"Win": 0.0, "Draw": 0.0, "Loss": 1.0}, "Santos": {"Win": 0.0, "Draw": 0.0, "Loss": 1.0}, "Athletico-PR": {"Win": 0.0, "Draw": 0.0, "Loss": 1.0}, "Atletico-MG": {"Win": 0.0, "Draw": 0.0, "Loss": 1.0}, "Goias": {"Win": 1.0, "Draw": 0.0, "Loss": 0.0}, "Figueirense": {"Win": 0.0, "Draw": 0.5, "Loss": 0.5}, "Corinthians": {"Win": 1.0, "Draw": 0.0, "Loss": 0.0}, "America-RN": {"Win": 1.0, "Draw": 0.0, "Loss": 0.0}, "Nautico": {"Win": 0.0, "Draw": 1.0, "Loss": 0.0}, "Sao Paulo": {"Win": 0.0, "Draw": 0.0, "Loss": 1.0}, "Cruzeiro": {"Win": 0.0, "Draw": 0.0, "Loss": 1.0}, "Juventude": {"Win": 0.0, "Draw": 0.0, "Loss": 1.0}, "Botafogo-RJ": {"Win": 0.0, "Draw": 0.5, "Loss": 0.5}, "Flamengo": {"Win": 0.0, "Draw": 0.5, "Loss": 0.5}, "Palmeiras": {"Win": 0.0, "Draw": 0.0, "Loss": 1.0}, "Internacional": {"Win": 0.5, "Draw": 0.0, "Loss": 0.5}, "Parana": {"Win": 0.0, "Draw": 1.0, "Loss": 0.0}, "Portuguesa": {"Win": 1.0, "Draw": 0.0, "Loss": 0.0}, "Ipatinga": {"Win": 0.0, "Draw": 0.0, "Loss": 1.0}, "Coritiba": {"Win": 1.0, "Draw": 0.0, "Loss": 0.0}, "Vitoria": {"Win": 0.0, "Draw": 0.0, "Loss": 1.0}}, "Vitoria": {"Cruzeiro": {"Win": 0.0, "Draw": 0.0, "Loss": 1.0}, "Figueirense": {"Win": 1.0, "Draw": 0.0, "Loss": 0.0}, "Santos": {"Win": 0.0, "Draw": 0.0, "Loss": 1.0}, "Internacional": {"Win": 0.0, "Draw": 0.0, "Loss": 1.0}, "Goias": {"Win": 0.0, "Draw": 0.0, "Loss": 1.0}, "Botafogo-RJ": {"Win": 0.0, "Draw": 0.0, "Loss": 1.0}, "Sao Paulo": {"Win": 0.0, "Draw": 0.0, "Loss": 1.0}, "Nautico": {"Win": 0.0, "Draw": 0.0, "Loss": 1.0}, "Athletico-PR": {"Win": 0.0, "Draw": 0.0, "Loss": 1.0}, "Vasco": {"Win": 1.0, "Draw": 0.0, "Loss": 0.0}, "Sport": {"Win": 0.0, "Draw": 1.0, "Loss": 0.0}, "Ipatinga": {"Win": 0.0, "Draw": 0.0, "Loss": 1.0}, "Coritiba": {"Win": 0.0, "Draw": 1.0, "Loss": 0.0}, "Portuguesa": {"Win": 1.0, "Draw": 0.0, "Loss": 0.0}, "Fluminense": {"Win": 0.0, "Draw": 0.0, "Loss": 1.0}, "Flamengo": {"Win": 1.0, "Draw": 0.0, "Loss": 0.0}, "Atletico-MG": {"Win": 0.0, "Draw": 0.0, "Loss": 1.0}, "Gremio": {"Win": 0.0, "Draw": 0.0, "Loss": 1.0}, "Palmeiras": {"Win": 0.0, "Draw": 0.0, "Loss": 1.0}}, "Coritiba": {"Palmeiras": {"Win": 0.0, "Draw": 0.0, "Loss": 1.0}, "Cruzeiro": {"Win": 0.0, "Draw": 1.0, "Loss": 0.0}, "Vitoria": {"Win": 0.0, "Draw": 0.0, "Loss": 1.0}, "Fluminense": {"Win": 1.0, "Draw": 0.0, "Loss": 0.0}, "Portuguesa": {"Win": 0.0, "Draw": 1.0, "Loss": 0.0}, "Flamengo": {"Win": 0.0, "Draw": 0.0, "Loss": 1.0}, "Ipatinga": {"Win": 0.0, "Draw": 0.0, "Loss": 1.0}, "Gremio": {"Win": 0.0, "Draw": 0.0, "Loss": 1.0}, "Sport": {"Win": 0.0, "Draw": 0.0, "Loss": 1.0}, "Figueirense": {"Win": 0.0, "Draw": 0.0, "Loss": 1.0}, "Sao Paulo": {"Win": 0.0, "Draw": 1.0, "Loss": 0.0}, "Botafogo-RJ": {"Win": 0.0, "Draw": 0.0, "Loss": 1.0}, "Athletico-PR": {"Win": 0.0, "Draw": 1.0, "Loss": 0.0}, "Internacional": {"Win": 0.0, "Draw": 0.0, "Loss": 1.0}, "Goias": {"Win": 0.0, "Draw": 1.0, "Loss": 0.0}, "Atletico-MG": {"Win": 0.0, "Draw": 0.0, "Loss": 1.0}, "Nautico": {"Win": 1.0, "Draw": 0.0, "Loss": 0.0}, "Santos": {"Win": 1.0, "Draw": 0.0, "Loss": 0.0}, "Vasco": {"Win": 1.0, "Draw": 0.0, "Loss": 0.0}}, "Ipatinga": {"Athletico-PR": {"Win": 0.0, "Draw": 0.0, "Loss": 1.0}, "Vitoria": {"Win": 0.0, "Draw": 1.0, "Loss": 0.0}, "Nautico": {"Win": 0.0, "Draw": 0.0, "Loss": 1.0}, "Flamengo": {"Win": 0.0, "Draw": 0.0, "Loss": 1.0}, "Figueirense": {"Win": 0.0, "Draw": 1.0, "Loss": 0.0}, "Cruzeiro": {"Win": 0.0, "Draw": 0.0, "Loss": 1.0}, "Portuguesa": {"Win": 0.0, "Draw": 0.0, "Loss": 1.0}, "Internacional": {"Win": 0.0, "Draw": 0.0, "Loss": 1.0}, "Palmeiras": {"Win": 0.0, "Draw": 0.0, "Loss": 1.0}, "Fluminense": {"Win": 0.0, "Draw": 1.0, "Loss": 0.0}, "Santos": {"Win": 0.0, "Draw": 0.0, "Loss": 1.0}, "Goias": {"Win": 0.0, "Draw": 1.0, "Loss": 0.0}, "Atletico-MG": {"Win": 0.0, "Draw": 0.0, "Loss": 1.0}, "Vasco": {"Win": 0.0, "Draw": 0.0, "Loss": 1.0}, "Sao Paulo": {"Win": 0.0, "Draw": 1.0, "Loss": 0.0}, "Botafogo-RJ": {"Win": 0.0, "Draw": 0.0, "Loss": 1.0}, "Coritiba": {"Win": 0.0, "Draw": 0.0, "Loss": 1.0}, "Sport": {"Win": 0.0, "Draw": 0.0, "Loss": 1.0}, "Gremio": {"Win": 0.0, "Draw": 0.0, "Loss": 1.0}}, "Portuguesa": {"Figueirense": {"Win": 0.0, "Draw": 0.0, "Loss": 1.0}, "Palmeiras": {"Win": 0.0, "Draw": 0.0, "Loss": 1.0}, "Internacional": {"Win": 0.0, "Draw": 0.0, "Loss": 1.0}, "Athletico-PR": {"Win": 0.0, "Draw": 0.0, "Loss": 1.0}, "Santos": {"Win": 0.0, "Draw": 1.0, "Loss": 0.0}, "Vitoria": {"Win": 0.0, "Draw": 0.0, "Loss": 1.0}, "Nautico": {"Win": 0.0, "Draw": 1.0, "Loss": 0.0}, "Flamengo": {"Win": 0.0, "Draw": 1.0, "Loss": 0.0}, "Fluminense": {"Win": 0.0, "Draw": 0.0, "Loss": 1.0}, "Cruzeiro": {"Win": 0.0, "Draw": 0.0, "Loss": 1.0}, "Vasco": {"Win": 0.0, "Draw": 0.0, "Loss": 1.0}, "Atletico-MG": {"Win": 0.0, "Draw": 0.0, "Loss": 1.0}, "Botafogo-RJ": {"Win": 1.0, "Draw": 0.0, "Loss": 0.0}, "Coritiba": {"Win": 0.0, "Draw": 0.0, "Loss": 1.0}, "Gremio": {"Win": 0.0, "Draw": 0.0, "Loss": 1.0}, "Ipatinga": {"Win": 0.0, "Draw": 0.0, "Loss": 1.0}, "Sao Paulo": {"Win": 0.0, "Draw": 0.0, "Loss": 1.0}, "Goias": {"Win": 0.0, "Draw": 0.0, "Loss": 1.0}, "Sport": {"Win": 0.0, "Draw": 0.0, "Loss": 1.0}}}